<?xml version="1.0" encoding="UTF-8"?>
<objects serializationModel="Studio.02.00.00">
	<object class="AudioFile" id="{00c5c5e4-b639-45d7-ba7f-78fc7bb39b16}">
		<property name="assetPath">
			<value>Interactions/Train/Train_StopSqueak.wav</value>
		</property>
		<property name="frequencyInKHz">
			<value>48</value>
		</property>
		<property name="channelCount">
			<value>1</value>
		</property>
		<property name="length">
			<value>0.66822916666666665</value>
		</property>
		<relationship name="masterAssetFolder">
			<destination>{901c69ff-b09e-4fb8-b7d9-d97094e64553}</destination>
		</relationship>
	</object>
</objects>
