<?xml version="1.0" encoding="UTF-8"?>
<objects serializationModel="Studio.02.00.00">
	<object class="AudioFile" id="{4d118c17-5b97-4bd2-83fc-5c5260c1118a}">
		<property name="assetPath">
			<value>EnvironmentalSFX/Gate/Gate_OpeningLoop.wav</value>
		</property>
		<property name="frequencyInKHz">
			<value>44.0999985</value>
		</property>
		<property name="channelCount">
			<value>1</value>
		</property>
		<property name="length">
			<value>8.3203174603174599</value>
		</property>
		<relationship name="masterAssetFolder">
			<destination>{901c69ff-b09e-4fb8-b7d9-d97094e64553}</destination>
		</relationship>
	</object>
</objects>
